pmtw/__init__.py
pmtw/classic.py
pmtw/constants.py
pmtw/puni.py
pmtw/settings.py
pmtw/stream.py
pmtw/toolbox.py
pmtw/usernotes.py
pmtw-1.1.3.dist-info/LICENSE.txt
pmtw-1.1.3.dist-info/METADATA
pmtw-1.1.3.dist-info/WHEEL
pmtw-1.1.3.dist-info/top_level.txt
pmtw-1.1.3.dist-info/RECORD
