Metadata-Version: 2.1
Name: pmtw
Version: 1.1.3
Summary: PMTW allows for simple access to Reddit Moderator Toolbox
Author-email: adhesiveCheese <adhesiveCheese@gmail.com>
License: Copyright (c) 2021. 2022 adhesiveCheese
Project-URL: Homepage, https://github.com/adhesivecheese/pmtw
Keywords: Reddit,Moderator_Toolbox,Web Wrapper
Classifier: Environment :: Console
Classifier: Intended Audience :: Developers
Classifier: License :: OSI Approved :: BSD License
Classifier: Natural Language :: English
Classifier: Operating System :: OS Independent
Classifier: Programming Language :: Python
Classifier: Programming Language :: Python :: 3
Classifier: Programming Language :: Python :: 3.7
Classifier: Programming Language :: Python :: 3.8
Classifier: Programming Language :: Python :: 3.9
Classifier: Programming Language :: Python :: 3.10
Classifier: Topic :: Utilities
Requires-Python: >=3.7
License-File: LICENSE.txt
Requires-Dist: praw (>=7.0)
